README.rst
setup.py
pyKurtuba/__init__.py
pyKurtuba/api.py
pyKurtuba.egg-info/PKG-INFO
pyKurtuba.egg-info/SOURCES.txt
pyKurtuba.egg-info/dependency_links.txt
pyKurtuba.egg-info/requires.txt
pyKurtuba.egg-info/top_level.txt