Metadata-Version: 1.0
Name: pyKurtuba
Version: 0.1.5
Summary: Python api-client for Kurtuba 
Home-page: https://github.com/gadzhi/pyKurtuba
Author: Gadzhibala Pirmagomedov
Author-email: gadzhibala@protonmail.com
License: UNKNOWN
Platform: UNKNOWN
